basiccalculator/__init__.py
karimstestcalculator-0.0.4.dist-info/licenses/LICENCE.txt
karimstestcalculator-0.0.4.dist-info/METADATA
karimstestcalculator-0.0.4.dist-info/WHEEL
karimstestcalculator-0.0.4.dist-info/top_level.txt
karimstestcalculator-0.0.4.dist-info/RECORD
